danecode/__init__.py
danecode/country_data.py
danecode/files/__init__.py
danecode/files/departamentos.csv
danecode/files/centros_poblados/05.csv
danecode/files/centros_poblados/08.csv
danecode/files/centros_poblados/11.csv
danecode/files/centros_poblados/13.csv
danecode/files/centros_poblados/15.csv
danecode/files/centros_poblados/17.csv
danecode/files/centros_poblados/18.csv
danecode/files/centros_poblados/19.csv
danecode/files/centros_poblados/20.csv
danecode/files/centros_poblados/23.csv
danecode/files/centros_poblados/25.csv
danecode/files/centros_poblados/27.csv
danecode/files/centros_poblados/41.csv
danecode/files/centros_poblados/44.csv
danecode/files/centros_poblados/47.csv
danecode/files/centros_poblados/50.csv
danecode/files/centros_poblados/52.csv
danecode/files/centros_poblados/54.csv
danecode/files/centros_poblados/63.csv
danecode/files/centros_poblados/66.csv
danecode/files/centros_poblados/68.csv
danecode/files/centros_poblados/70.csv
danecode/files/centros_poblados/73.csv
danecode/files/centros_poblados/76.csv
danecode/files/centros_poblados/81.csv
danecode/files/centros_poblados/85.csv
danecode/files/centros_poblados/86.csv
danecode/files/centros_poblados/88.csv
danecode/files/centros_poblados/91.csv
danecode/files/centros_poblados/94.csv
danecode/files/centros_poblados/95.csv
danecode/files/centros_poblados/97.csv
danecode/files/centros_poblados/99.csv
danecode/files/centros_poblados/__init__.py
danecode/services/__init__.py
danecode-0.2.11.dist-info/LICENSE
danecode-0.2.11.dist-info/METADATA
danecode-0.2.11.dist-info/WHEEL
danecode-0.2.11.dist-info/top_level.txt
danecode-0.2.11.dist-info/RECORD
