Metadata-Version: 2.1
Name: danecode
Version: 0.2.11
Summary: A simple util to get dane codes by department and municipality
Author: santiagofep
Classifier: Programming Language :: Python :: 3
Classifier: License :: OSI Approved :: MIT License
Classifier: Operating System :: OS Independent
Requires-Python: >=3.6
License-File: LICENSE
Requires-Dist: jellyfish
Requires-Dist: pandas
Requires-Dist: unidecode
